MANIFEST.in
README.md
setup.py
dash_daq/BooleanSwitch.py
dash_daq/ColorPicker.py
dash_daq/DarkThemeProvider.py
dash_daq/Gauge.py
dash_daq/GraduatedBar.py
dash_daq/Indicator.py
dash_daq/Joystick.py
dash_daq/Knob.py
dash_daq/LEDDisplay.py
dash_daq/NumericInput.py
dash_daq/PowerButton.py
dash_daq/PrecisionInput.py
dash_daq/Slider.py
dash_daq/StopButton.py
dash_daq/Tank.py
dash_daq/Thermometer.py
dash_daq/ToggleSwitch.py
dash_daq/__init__.py
dash_daq/_imports_.py
dash_daq/async-colorpicker.js
dash_daq/async-colorpicker.js.map
dash_daq/async-slider.js
dash_daq/async-slider.js.map
dash_daq/dash_daq.min.js
dash_daq/dash_daq.min.js.map
dash_daq/metadata.json
dash_daq/package-info.json
dash_daq.egg-info/PKG-INFO
dash_daq.egg-info/SOURCES.txt
dash_daq.egg-info/dependency_links.txt
dash_daq.egg-info/requires.txt
dash_daq.egg-info/top_level.txt