Metadata-Version: 2.1
Name: dash_daq
Version: 0.4.0
Summary: DAQ components for Dash
Home-page: http://github.com/plotly/dash-daq
Author: The Plotly Team <dashdaq@plot.ly>
Author-email: dashdaq@plot.ly
License: UNKNOWN
Platform: UNKNOWN
Classifier: Programming Language :: Python :: 3
Classifier: License :: OSI Approved :: MIT License
Classifier: Operating System :: OS Independent
